LICENSE.rst
MANIFEST.in
README.rst
setup.py
src/node/__init__.py
src/node.ext.python.egg-info/PKG-INFO
src/node.ext.python.egg-info/SOURCES.txt
src/node.ext.python.egg-info/dependency_links.txt
src/node.ext.python.egg-info/entry_points.txt
src/node.ext.python.egg-info/namespace_packages.txt
src/node.ext.python.egg-info/not-zip-safe
src/node.ext.python.egg-info/requires.txt
src/node.ext.python.egg-info/top_level.txt
src/node/ext/__init__.py
src/node/ext/python/__init__.py
src/node/ext/python/edgecases.rst
src/node/ext/python/goparser.py
src/node/ext/python/goparser.rst
src/node/ext/python/interfaces.py
src/node/ext/python/nodes.py
src/node/ext/python/nodes.rst
src/node/ext/python/parser.py
src/node/ext/python/parser.rst
src/node/ext/python/renderer.py
src/node/ext/python/renderer.rst
src/node/ext/python/tests.py
src/node/ext/python/utils.py
src/node/ext/python/utils.rst
src/node/ext/python/testing/__init__.py
src/node/ext/python/testing/data/__init_.py
src/node/ext/python/testing/data/changed.py
src/node/ext/python/testing/data/class_wo_functions.py
src/node/ext/python/testing/data/edgecases.py
src/node/ext/python/testing/data/moved.py
src/node/ext/python/testing/data/nullbyte.py
src/node/ext/python/testing/data/parseme.py
src/node/ext/python/testing/data/rendered.py
src/node/ext/python/testing/data/unchanged.py